common/__init__.py
common/logger.py
common/utilities/__init__.py
common/utilities/function_helper.py
nrg_parser/__init__.py
nrg_parser/mast/__init__.py
nrg_parser/mast/constants/__init__.py
nrg_parser/mast/constants/iea_mapping_config.py
nrg_parser/mast/logger_model/__init__.py
nrg_parser/mast/logger_model/nrg/__init__.py
nrg_parser/mast/logger_model/nrg/reader/__init__.py
nrg_parser/mast/logger_model/nrg/reader/symphoniepro_txt_reader.py
nrg_parser/mast/utilities/__init__.py
nrg_parser/mast/utilities/iea_json/__init__.py
nrg_parser/mast/utilities/iea_json/convert_to_iea_json.py
nrg_parser/mast/utilities/iea_json/create_iea_json_nrg.py
nrg_parser/mast/utilities/iea_json/iea_models.py
nrg_parser/mast/utilities/iea_json/nrg_config.py
nrg_parser-0.1.1.dist-info/LICENSE
nrg_parser-0.1.1.dist-info/METADATA
nrg_parser-0.1.1.dist-info/WHEEL
nrg_parser-0.1.1.dist-info/RECORD
