Metadata-Version: 2.1
Name: nrg-parser
Version: 0.1.1
Summary: IEA task 43 parsers for NRG Systems, Inc. SymphoniePRO loggers
License: MIT
Keywords: wind-energy,iea-task-43,nrg-systems,symphonie,symphoniepro
Author: David Carlson
Author-email: drc@nrgsystems.com
Requires-Python: >=3.10,<4.0
Classifier: License :: OSI Approved :: MIT License
Classifier: Operating System :: OS Independent
Classifier: Programming Language :: Python
Classifier: Programming Language :: Python :: 3
Classifier: Programming Language :: Python :: 3.10
Classifier: Programming Language :: Python :: 3.11
Requires-Dist: nrgpy (>=1.8.4,<2.0.0)
Requires-Dist: numpy (>=1.23.4,<2.0.0)
Requires-Dist: pandas (>=2)
Requires-Dist: pyarrow (>=10.0.1,<11.0.0)
Requires-Dist: python-dateutil (>=2.8.2,<3.0.0)
